{
    "behavior_code": 0,
    "consume_item_id": 2,
    "consume_item_type": 99,
    "nonce": "xF5FL2L2j8XAc5Lc",
    "products": [
        {
            "close_date": 1924905600000,
            "consume_item_id": 2,
            "consume_item_id2": -1,
            "consume_item_id3": -1,
            "consume_item_id4": -1,
            "consume_item_id5": -1,
            "consume_item_type": 99,
            "consume_item_type2": -1,
            "consume_item_type3": -1,
            "consume_item_type4": -1,
            "consume_item_type5": -1,
            "description": "",
            "eqsi_id": 313272,
            "exchange": 0,
            "exchange_limit_once": 4,
            "grant_type": 0,
            "icon": 0,
            "item_id": 1401,
            "item_name": "Knight's Armor (I)",
            "item_type": 2,
            "new_date": 1483228800000,
            "num": 1,
            "price": 10,
            "price2": 0,
            "price3": 0,
            "price4": 0,
            "price5": 0,
            "price_gil": 0,
            "published_date": 1647936000000,
            "shop_type": 1431,
            "sort_num": 1,
            "stock": 0,
            "tab_group": -1
        },
        {
            "close_date": 1924905600000,
            "consume_item_id": 2,
            "consume_item_id2": -1,
            "consume_item_id3": -1,
            "consume_item_id4": -1,
            "consume_item_id5": -1,
            "consume_item_type": 99,
            "consume_item_type2": -1,
            "consume_item_type3": -1,
            "consume_item_type4": -1,
            "consume_item_type5": -1,
            "description": "",
            "eqsi_id": 313273,
            "exchange": 0,
            "exchange_limit_once": 4,
            "grant_type": 0,
            "icon": 0,
            "item_id": 1423,
            "item_name": "Power Armlet (II)",
            "item_type": 2,
            "new_date": 1483228800000,
            "num": 1,
            "price": 10,
            "price2": 0,
            "price3": 0,
            "price4": 0,
            "price5": 0,
            "price_gil": 0,
            "published_date": 1647936000000,
            "shop_type": 1431,
            "sort_num": 2,
            "stock": 0,
            "tab_group": -1
        },
        {
            "close_date": 1924905600000,
            "consume_item_id": 2,
            "consume_item_id2": -1,
            "consume_item_id3": -1,
            "consume_item_id4": -1,
            "consume_item_id5": -1,
            "consume_item_type": 99,
            "consume_item_type2": -1,
            "consume_item_type3": -1,
            "consume_item_type4": -1,
            "consume_item_type5": -1,
            "description": "",
            "eqsi_id": 313274,
            "exchange": 0,
            "exchange_limit_once": 4,
            "grant_type": 0,
            "icon": 0,
            "item_id": 1420,
            "item_name": "Shell Helm (III)",
            "item_type": 2,
            "new_date": 1483228800000,
            "num": 1,
            "price": 10,
            "price2": 0,
            "price3": 0,
            "price4": 0,
            "price5": 0,
            "price_gil": 0,
            "published_date": 1647936000000,
            "shop_type": 1431,
            "sort_num": 3,
            "stock": 0,
            "tab_group": -1
        },
        {
            "close_date": 1924905600000,
            "consume_item_id": 2,
            "consume_item_id2": -1,
            "consume_item_id3": -1,
            "consume_item_id4": -1,
            "consume_item_id5": -1,
            "consume_item_type": 99,
            "consume_item_type2": -1,
            "consume_item_type3": -1,
            "consume_item_type4": -1,
            "consume_item_type5": -1,
            "description": "",
            "eqsi_id": 313275,
            "exchange": 0,
            "exchange_limit_once": 4,
            "grant_type": 0,
            "icon": 0,
            "item_id": 1425,
            "item_name": "Dark Armor (IV)",
            "item_type": 2,
            "new_date": 1483228800000,
            "num": 1,
            "price": 10,
            "price2": 0,
            "price3": 0,
            "price4": 0,
            "price5": 0,
            "price_gil": 0,
            "published_date": 1647936000000,
            "shop_type": 1431,
            "sort_num": 4,
            "stock": 0,
            "tab_group": -1
        },
        {
            "close_date": 1924905600000,
            "consume_item_id": 2,
            "consume_item_id2": -1,
            "consume_item_id3": -1,
            "consume_item_id4": -1,
            "consume_item_id5": -1,
            "consume_item_type": 99,
            "consume_item_type2": -1,
            "consume_item_type3": -1,
            "consume_item_type4": -1,
            "consume_item_type5": -1,
            "description": "",
            "eqsi_id": 313276,
            "exchange": 0,
            "exchange_limit_once": 4,
            "grant_type": 0,
            "icon": 0,
            "item_id": 1414,
            "item_name": "Twisted Headband (IV)",
            "item_type": 2,
            "new_date": 1483228800000,
            "num": 1,
            "price": 10,
            "price2": 0,
            "price3": 0,
            "price4": 0,
            "price5": 0,
            "price_gil": 0,
            "published_date": 1647936000000,
            "shop_type": 1431,
            "sort_num": 5,
            "stock": 0,
            "tab_group": -1
        },
        {
            "close_date": 1924905600000,
            "consume_item_id": 2,
            "consume_item_id2": -1,
            "consume_item_id3": -1,
            "consume_item_id4": -1,
            "consume_item_id5": -1,
            "consume_item_type": 99,
            "consume_item_type2": -1,
            "consume_item_type3": -1,
            "consume_item_type4": -1,
            "consume_item_type5": -1,
            "description": "",
            "eqsi_id": 313277,
            "exchange": 0,
            "exchange_limit_once": 4,
            "grant_type": 0,
            "icon": 0,
            "item_id": 1419,
            "item_name": "Kenpo Gi (IV)",
            "item_type": 2,
            "new_date": 1483228800000,
            "num": 1,
            "price": 10,
            "price2": 0,
            "price3": 0,
            "price4": 0,
            "price5": 0,
            "price_gil": 0,
            "published_date": 1647936000000,
            "shop_type": 1431,
            "sort_num": 6,
            "stock": 0,
            "tab_group": -1
        },
        {
            "close_date": 1924905600000,
            "consume_item_id": 2,
            "consume_item_id2": -1,
            "consume_item_id3": -1,
            "consume_item_id4": -1,
            "consume_item_id5": -1,
            "consume_item_type": 99,
            "consume_item_type2": -1,
            "consume_item_type3": -1,
            "consume_item_type4": -1,
            "consume_item_type5": -1,
            "description": "",
            "eqsi_id": 313278,
            "exchange": 0,
            "exchange_limit_once": 4,
            "grant_type": 0,
            "icon": 0,
            "item_id": 1413,
            "item_name": "Green Beret (V)",
            "item_type": 2,
            "new_date": 1483228800000,
            "num": 1,
            "price": 10,
            "price2": 0,
            "price3": 0,
            "price4": 0,
            "price5": 0,
            "price_gil": 0,
            "published_date": 1647936000000,
            "shop_type": 1431,
            "sort_num": 7,
            "stock": 0,
            "tab_group": -1
        },
        {
            "close_date": 1924905600000,
            "consume_item_id": 2,
            "consume_item_id2": -1,
            "consume_item_id3": -1,
            "consume_item_id4": -1,
            "consume_item_id5": -1,
            "consume_item_type": 99,
            "consume_item_type2": -1,
            "consume_item_type3": -1,
            "consume_item_type4": -1,
            "consume_item_type5": -1,
            "description": "",
            "eqsi_id": 313279,
            "exchange": 0,
            "exchange_limit_once": 4,
            "grant_type": 0,
            "icon": 0,
            "item_id": 1438,
            "item_name": "Gauntlets (V)",
            "item_type": 2,
            "new_date": 1483228800000,
            "num": 1,
            "price": 10,
            "price2": 0,
            "price3": 0,
            "price4": 0,
            "price5": 0,
            "price_gil": 0,
            "published_date": 1647936000000,
            "shop_type": 1431,
            "sort_num": 8,
            "stock": 0,
            "tab_group": -1
        },
        {
            "close_date": 1924905600000,
            "consume_item_id": 2,
            "consume_item_id2": -1,
            "consume_item_id3": -1,
            "consume_item_id4": -1,
            "consume_item_id5": -1,
            "consume_item_type": 99,
            "consume_item_type2": -1,
            "consume_item_type3": -1,
            "consume_item_type4": -1,
            "consume_item_type5": -1,
            "description": "",
            "eqsi_id": 313280,
            "exchange": 0,
            "exchange_limit_once": 4,
            "grant_type": 0,
            "icon": 0,
            "item_id": 1442,
            "item_name": "Silver Plate (V)",
            "item_type": 2,
            "new_date": 1483228800000,
            "num": 1,
            "price": 10,
            "price2": 0,
            "price3": 0,
            "price4": 0,
            "price5": 0,
            "price_gil": 0,
            "published_date": 1647936000000,
            "shop_type": 1431,
            "sort_num": 9,
            "stock": 0,
            "tab_group": -1
        },
        {
            "close_date": 1924905600000,
            "consume_item_id": 2,
            "consume_item_id2": -1,
            "consume_item_id3": -1,
            "consume_item_id4": -1,
            "consume_item_id5": -1,
            "consume_item_type": 99,
            "consume_item_type2": -1,
            "consume_item_type3": -1,
            "consume_item_type4": -1,
            "consume_item_type5": -1,
            "description": "",
            "eqsi_id": 313281,
            "exchange": 0,
            "exchange_limit_once": 4,
            "grant_type": 0,
            "icon": 0,
            "item_id": 1417,
            "item_name": "Jeweled Ring (VI)",
            "item_type": 2,
            "new_date": 1483228800000,
            "num": 1,
            "price": 10,
            "price2": 0,
            "price3": 0,
            "price4": 0,
            "price5": 0,
            "price_gil": 0,
            "published_date": 1647936000000,
            "shop_type": 1431,
            "sort_num": 10,
            "stock": 0,
            "tab_group": -1
        },
        {
            "close_date": 1924905600000,
            "consume_item_id": 2,
            "consume_item_id2": -1,
            "consume_item_id3": -1,
            "consume_item_id4": -1,
            "consume_item_id5": -1,
            "consume_item_type": 99,
            "consume_item_type2": -1,
            "consume_item_type3": -1,
            "consume_item_type4": -1,
            "consume_item_type5": -1,
            "description": "",
            "eqsi_id": 313282,
            "exchange": 0,
            "exchange_limit_once": 4,
            "grant_type": 0,
            "icon": 0,
            "item_id": 1421,
            "item_name": "Ninja Gear (VI)",
            "item_type": 2,
            "new_date": 1483228800000,
            "num": 1,
            "price": 10,
            "price2": 0,
            "price3": 0,
            "price4": 0,
            "price5": 0,
            "price_gil": 0,
            "published_date": 1647936000000,
            "shop_type": 1431,
            "sort_num": 11,
            "stock": 0,
            "tab_group": -1
        },
        {
            "close_date": 1924905600000,
            "consume_item_id": 2,
            "consume_item_id2": -1,
            "consume_item_id3": -1,
            "consume_item_id4": -1,
            "consume_item_id5": -1,
            "consume_item_type": 99,
            "consume_item_type2": -1,
            "consume_item_type3": -1,
            "consume_item_type4": -1,
            "consume_item_type5": -1,
            "description": "",
            "eqsi_id": 313283,
            "exchange": 0,
            "exchange_limit_once": 4,
            "grant_type": 0,
            "icon": 0,
            "item_id": 1432,
            "item_name": "Amulet (VI)",
            "item_type": 2,
            "new_date": 1483228800000,
            "num": 1,
            "price": 10,
            "price2": 0,
            "price3": 0,
            "price4": 0,
            "price5": 0,
            "price_gil": 0,
            "published_date": 1647936000000,
            "shop_type": 1431,
            "sort_num": 12,
            "stock": 0,
            "tab_group": -1
        },
        {
            "close_date": 1924905600000,
            "consume_item_id": 2,
            "consume_item_id2": -1,
            "consume_item_id3": -1,
            "consume_item_id4": -1,
            "consume_item_id5": -1,
            "consume_item_type": 99,
            "consume_item_type2": -1,
            "consume_item_type3": -1,
            "consume_item_type4": -1,
            "consume_item_type5": -1,
            "description": "",
            "eqsi_id": 313284,
            "exchange": 0,
            "exchange_limit_once": 4,
            "grant_type": 0,
            "icon": 0,
            "item_id": 1453,
            "item_name": "Power Vest (VI)",
            "item_type": 2,
            "new_date": 1483228800000,
            "num": 1,
            "price": 10,
            "price2": 0,
            "price3": 0,
            "price4": 0,
            "price5": 0,
            "price_gil": 0,
            "published_date": 1647936000000,
            "shop_type": 1431,
            "sort_num": 13,
            "stock": 0,
            "tab_group": -1
        },
        {
            "close_date": 1924905600000,
            "consume_item_id": 2,
            "consume_item_id2": -1,
            "consume_item_id3": -1,
            "consume_item_id4": -1,
            "consume_item_id5": -1,
            "consume_item_type": 99,
            "consume_item_type2": -1,
            "consume_item_type3": -1,
            "consume_item_type4": -1,
            "consume_item_type5": -1,
            "description": "",
            "eqsi_id": 313285,
            "exchange": 0,
            "exchange_limit_once": 4,
            "grant_type": 0,
            "icon": 0,
            "item_id": 1455,
            "item_name": "Golden Armor (VI)",
            "item_type": 2,
            "new_date": 1483228800000,
            "num": 1,
            "price": 10,
            "price2": 0,
            "price3": 0,
            "price4": 0,
            "price5": 0,
            "price_gil": 0,
            "published_date": 1647936000000,
            "shop_type": 1431,
            "sort_num": 14,
            "stock": 0,
            "tab_group": -1
        },
        {
            "close_date": 1924905600000,
            "consume_item_id": 2,
            "consume_item_id2": -1,
            "consume_item_id3": -1,
            "consume_item_id4": -1,
            "consume_item_id5": -1,
            "consume_item_type": 99,
            "consume_item_type2": -1,
            "consume_item_type3": -1,
            "consume_item_type4": -1,
            "consume_item_type5": -1,
            "description": "",
            "eqsi_id": 313286,
            "exchange": 0,
            "exchange_limit_once": 4,
            "grant_type": 0,
            "icon": 0,
            "item_id": 1406,
            "item_name": "Shinra Beta (VII)",
            "item_type": 2,
            "new_date": 1483228800000,
            "num": 1,
            "price": 10,
            "price2": 0,
            "price3": 0,
            "price4": 0,
            "price5": 0,
            "price_gil": 0,
            "published_date": 1647936000000,
            "shop_type": 1431,
            "sort_num": 15,
            "stock": 0,
            "tab_group": -1
        },
        {
            "close_date": 1924905600000,
            "consume_item_id": 2,
            "consume_item_id2": -1,
            "consume_item_id3": -1,
            "consume_item_id4": -1,
            "consume_item_id5": -1,
            "consume_item_type": 99,
            "consume_item_type2": -1,
            "consume_item_type3": -1,
            "consume_item_type4": -1,
            "consume_item_type5": -1,
            "description": "",
            "eqsi_id": 313287,
            "exchange": 0,
            "exchange_limit_once": 4,
            "grant_type": 0,
            "icon": 0,
            "item_id": 1405,
            "item_name": "Power Armband (VII)",
            "item_type": 2,
            "new_date": 1483228800000,
            "num": 1,
            "price": 10,
            "price2": 0,
            "price3": 0,
            "price4": 0,
            "price5": 0,
            "price_gil": 0,
            "published_date": 1647936000000,
            "shop_type": 1431,
            "sort_num": 16,
            "stock": 0,
            "tab_group": -1
        },
        {
            "close_date": 1924905600000,
            "consume_item_id": 2,
            "consume_item_id2": -1,
            "consume_item_id3": -1,
            "consume_item_id4": -1,
            "consume_item_id5": -1,
            "consume_item_type": 99,
            "consume_item_type2": -1,
            "consume_item_type3": -1,
            "consume_item_type4": -1,
            "consume_item_type5": -1,
            "description": "",
            "eqsi_id": 313288,
            "exchange": 0,
            "exchange_limit_once": 4,
            "grant_type": 0,
            "icon": 0,
            "item_id": 1416,
            "item_name": "Silver Armlet (VII)",
            "item_type": 2,
            "new_date": 1483228800000,
            "num": 1,
            "price": 10,
            "price2": 0,
            "price3": 0,
            "price4": 0,
            "price5": 0,
            "price_gil": 0,
            "published_date": 1647936000000,
            "shop_type": 1431,
            "sort_num": 17,
            "stock": 0,
            "tab_group": -1
        },
        {
            "close_date": 1924905600000,
            "consume_item_id": 2,
            "consume_item_id2": -1,
            "consume_item_id3": -1,
            "consume_item_id4": -1,
            "consume_item_id5": -1,
            "consume_item_type": 99,
            "consume_item_type2": -1,
            "consume_item_type3": -1,
            "consume_item_type4": -1,
            "consume_item_type5": -1,
            "description": "",
            "eqsi_id": 313289,
            "exchange": 0,
            "exchange_limit_once": 4,
            "grant_type": 0,
            "icon": 0,
            "item_id": 1446,
            "item_name": "Scarlet Bandana (VII)",
            "item_type": 2,
            "new_date": 1483228800000,
            "num": 1,
            "price": 10,
            "price2": 0,
            "price3": 0,
            "price4": 0,
            "price5": 0,
            "price_gil": 0,
            "published_date": 1647936000000,
            "shop_type": 1431,
            "sort_num": 18,
            "stock": 0,
            "tab_group": -1
        },
        {
            "close_date": 1924905600000,
            "consume_item_id": 2,
            "consume_item_id2": -1,
            "consume_item_id3": -1,
            "consume_item_id4": -1,
            "consume_item_id5": -1,
            "consume_item_type": 99,
            "consume_item_type2": -1,
            "consume_item_type3": -1,
            "consume_item_type4": -1,
            "consume_item_type5": -1,
            "description": "",
            "eqsi_id": 313290,
            "exchange": 0,
            "exchange_limit_once": 4,
            "grant_type": 0,
            "icon": 0,
            "item_id": 1428,
            "item_name": "SeeD Uniform (VIII)",
            "item_type": 2,
            "new_date": 1483228800000,
            "num": 1,
            "price": 10,
            "price2": 0,
            "price3": 0,
            "price4": 0,
            "price5": 0,
            "price_gil": 0,
            "published_date": 1647936000000,
            "shop_type": 1431,
            "sort_num": 19,
            "stock": 0,
            "tab_group": -1
        },
        {
            "close_date": 1924905600000,
            "consume_item_id": 2,
            "consume_item_id2": -1,
            "consume_item_id3": -1,
            "consume_item_id4": -1,
            "consume_item_id5": -1,
            "consume_item_type": 99,
            "consume_item_type2": -1,
            "consume_item_type3": -1,
            "consume_item_type4": -1,
            "consume_item_type5": -1,
            "description": "",
            "eqsi_id": 313291,
            "exchange": 0,
            "exchange_limit_once": 4,
            "grant_type": 0,
            "icon": 0,
            "item_id": 1424,
            "item_name": "Galbadian Uniform (VIII)",
            "item_type": 2,
            "new_date": 1483228800000,
            "num": 1,
            "price": 10,
            "price2": 0,
            "price3": 0,
            "price4": 0,
            "price5": 0,
            "price_gil": 0,
            "published_date": 1647936000000,
            "shop_type": 1431,
            "sort_num": 20,
            "stock": 0,
            "tab_group": -1
        },
        {
            "close_date": 1924905600000,
            "consume_item_id": 2,
            "consume_item_id2": -1,
            "consume_item_id3": -1,
            "consume_item_id4": -1,
            "consume_item_id5": -1,
            "consume_item_type": 99,
            "consume_item_type2": -1,
            "consume_item_type3": -1,
            "consume_item_type4": -1,
            "consume_item_type5": -1,
            "description": "",
            "eqsi_id": 313292,
            "exchange": 0,
            "exchange_limit_once": 4,
            "grant_type": 0,
            "icon": 0,
            "item_id": 1444,
            "item_name": "Zell's Trousers (VIII)",
            "item_type": 2,
            "new_date": 1483228800000,
            "num": 1,
            "price": 10,
            "price2": 0,
            "price3": 0,
            "price4": 0,
            "price5": 0,
            "price_gil": 0,
            "published_date": 1647936000000,
            "shop_type": 1431,
            "sort_num": 21,
            "stock": 0,
            "tab_group": -1
        },
        {
            "close_date": 1924905600000,
            "consume_item_id": 2,
            "consume_item_id2": -1,
            "consume_item_id3": -1,
            "consume_item_id4": -1,
            "consume_item_id5": -1,
            "consume_item_type": 99,
            "consume_item_type2": -1,
            "consume_item_type3": -1,
            "consume_item_type4": -1,
            "consume_item_type5": -1,
            "description": "",
            "eqsi_id": 313293,
            "exchange": 0,
            "exchange_limit_once": 4,
            "grant_type": 0,
            "icon": 0,
            "item_id": 1456,
            "item_name": "Cowboy Hat (VIII)",
            "item_type": 2,
            "new_date": 1483228800000,
            "num": 1,
            "price": 10,
            "price2": 0,
            "price3": 0,
            "price4": 0,
            "price5": 0,
            "price_gil": 0,
            "published_date": 1647936000000,
            "shop_type": 1431,
            "sort_num": 22,
            "stock": 0,
            "tab_group": -1
        },
        {
            "close_date": 1924905600000,
            "consume_item_id": 2,
            "consume_item_id2": -1,
            "consume_item_id3": -1,
            "consume_item_id4": -1,
            "consume_item_id5": -1,
            "consume_item_type": 99,
            "consume_item_type2": -1,
            "consume_item_type3": -1,
            "consume_item_type4": -1,
            "consume_item_type5": -1,
            "description": "",
            "eqsi_id": 313294,
            "exchange": 0,
            "exchange_limit_once": 4,
            "grant_type": 0,
            "icon": 0,
            "item_id": 1457,
            "item_name": "Seifer's Gloves (VIII)",
            "item_type": 2,
            "new_date": 1483228800000,
            "num": 1,
            "price": 10,
            "price2": 0,
            "price3": 0,
            "price4": 0,
            "price5": 0,
            "price_gil": 0,
            "published_date": 1647936000000,
            "shop_type": 1431,
            "sort_num": 23,
            "stock": 0,
            "tab_group": -1
        },
        {
            "close_date": 1924905600000,
            "consume_item_id": 2,
            "consume_item_id2": -1,
            "consume_item_id3": -1,
            "consume_item_id4": -1,
            "consume_item_id5": -1,
            "consume_item_type": 99,
            "consume_item_type2": -1,
            "consume_item_type3": -1,
            "consume_item_type4": -1,
            "consume_item_type5": -1,
            "description": "",
            "eqsi_id": 313295,
            "exchange": 0,
            "exchange_limit_once": 4,
            "grant_type": 0,
            "icon": 0,
            "item_id": 1459,
            "item_name": "Raijin's Beads (VIII)",
            "item_type": 2,
            "new_date": 1483228800000,
            "num": 1,
            "price": 10,
            "price2": 0,
            "price3": 0,
            "price4": 0,
            "price5": 0,
            "price_gil": 0,
            "published_date": 1647936000000,
            "shop_type": 1431,
            "sort_num": 24,
            "stock": 0,
            "tab_group": -1
        },
        {
            "close_date": 1924905600000,
            "consume_item_id": 2,
            "consume_item_id2": -1,
            "consume_item_id3": -1,
            "consume_item_id4": -1,
            "consume_item_id5": -1,
            "consume_item_type": 99,
            "consume_item_type2": -1,
            "consume_item_type3": -1,
            "consume_item_type4": -1,
            "consume_item_type5": -1,
            "description": "",
            "eqsi_id": 313296,
            "exchange": 0,
            "exchange_limit_once": 4,
            "grant_type": 0,
            "icon": 0,
            "item_id": 1458,
            "item_name": "Fujin's Eyepatch (VIII)",
            "item_type": 2,
            "new_date": 1483228800000,
            "num": 1,
            "price": 10,
            "price2": 0,
            "price3": 0,
            "price4": 0,
            "price5": 0,
            "price_gil": 0,
            "published_date": 1647936000000,
            "shop_type": 1431,
            "sort_num": 25,
            "stock": 0,
            "tab_group": -1
        },
        {
            "close_date": 1924905600000,
            "consume_item_id": 2,
            "consume_item_id2": -1,
            "consume_item_id3": -1,
            "consume_item_id4": -1,
            "consume_item_id5": -1,
            "consume_item_type": 99,
            "consume_item_type2": -1,
            "consume_item_type3": -1,
            "consume_item_type4": -1,
            "consume_item_type5": -1,
            "description": "",
            "eqsi_id": 313297,
            "exchange": 0,
            "exchange_limit_once": 4,
            "grant_type": 0,
            "icon": 0,
            "item_id": 1409,
            "item_name": "Survival Vest (IX)",
            "item_type": 2,
            "new_date": 1483228800000,
            "num": 1,
            "price": 10,
            "price2": 0,
            "price3": 0,
            "price4": 0,
            "price5": 0,
            "price_gil": 0,
            "published_date": 1647936000000,
            "shop_type": 1431,
            "sort_num": 26,
            "stock": 0,
            "tab_group": -1
        },
        {
            "close_date": 1924905600000,
            "consume_item_id": 2,
            "consume_item_id2": -1,
            "consume_item_id3": -1,
            "consume_item_id4": -1,
            "consume_item_id5": -1,
            "consume_item_type": 99,
            "consume_item_type2": -1,
            "consume_item_type3": -1,
            "consume_item_type4": -1,
            "consume_item_type5": -1,
            "description": "",
            "eqsi_id": 313298,
            "exchange": 0,
            "exchange_limit_once": 4,
            "grant_type": 0,
            "icon": 0,
            "item_id": 1402,
            "item_name": "Pointy Hat (IX)",
            "item_type": 2,
            "new_date": 1483228800000,
            "num": 1,
            "price": 10,
            "price2": 0,
            "price3": 0,
            "price4": 0,
            "price5": 0,
            "price_gil": 0,
            "published_date": 1647936000000,
            "shop_type": 1431,
            "sort_num": 27,
            "stock": 0,
            "tab_group": -1
        },
        {
            "close_date": 1924905600000,
            "consume_item_id": 2,
            "consume_item_id2": -1,
            "consume_item_id3": -1,
            "consume_item_id4": -1,
            "consume_item_id5": -1,
            "consume_item_type": 99,
            "consume_item_type2": -1,
            "consume_item_type3": -1,
            "consume_item_type4": -1,
            "consume_item_type5": -1,
            "description": "",
            "eqsi_id": 313299,
            "exchange": 0,
            "exchange_limit_once": 4,
            "grant_type": 0,
            "icon": 0,
            "item_id": 1422,
            "item_name": "Linen Cuirass (IX)",
            "item_type": 2,
            "new_date": 1483228800000,
            "num": 1,
            "price": 10,
            "price2": 0,
            "price3": 0,
            "price4": 0,
            "price5": 0,
            "price_gil": 0,
            "published_date": 1647936000000,
            "shop_type": 1431,
            "sort_num": 28,
            "stock": 0,
            "tab_group": -1
        },
        {
            "close_date": 1924905600000,
            "consume_item_id": 2,
            "consume_item_id2": -1,
            "consume_item_id3": -1,
            "consume_item_id4": -1,
            "consume_item_id5": -1,
            "consume_item_type": 99,
            "consume_item_type2": -1,
            "consume_item_type3": -1,
            "consume_item_type4": -1,
            "consume_item_type5": -1,
            "description": "",
            "eqsi_id": 313300,
            "exchange": 0,
            "exchange_limit_once": 4,
            "grant_type": 0,
            "icon": 0,
            "item_id": 1440,
            "item_name": "Anklet (IX)",
            "item_type": 2,
            "new_date": 1483228800000,
            "num": 1,
            "price": 10,
            "price2": 0,
            "price3": 0,
            "price4": 0,
            "price5": 0,
            "price_gil": 0,
            "published_date": 1647936000000,
            "shop_type": 1431,
            "sort_num": 29,
            "stock": 0,
            "tab_group": -1
        },
        {
            "close_date": 1924905600000,
            "consume_item_id": 2,
            "consume_item_id2": -1,
            "consume_item_id3": -1,
            "consume_item_id4": -1,
            "consume_item_id5": -1,
            "consume_item_type": 99,
            "consume_item_type2": -1,
            "consume_item_type3": -1,
            "consume_item_type4": -1,
            "consume_item_type5": -1,
            "description": "",
            "eqsi_id": 313301,
            "exchange": 0,
            "exchange_limit_once": 4,
            "grant_type": 0,
            "icon": 0,
            "item_id": 1429,
            "item_name": "Seeker's Shield (X)",
            "item_type": 2,
            "new_date": 1483228800000,
            "num": 1,
            "price": 10,
            "price2": 0,
            "price3": 0,
            "price4": 0,
            "price5": 0,
            "price_gil": 0,
            "published_date": 1647936000000,
            "shop_type": 1431,
            "sort_num": 30,
            "stock": 0,
            "tab_group": -1
        },
        {
            "close_date": 1924905600000,
            "consume_item_id": 2,
            "consume_item_id2": -1,
            "consume_item_id3": -1,
            "consume_item_id4": -1,
            "consume_item_id5": -1,
            "consume_item_type": 99,
            "consume_item_type2": -1,
            "consume_item_type3": -1,
            "consume_item_type4": -1,
            "consume_item_type5": -1,
            "description": "",
            "eqsi_id": 313302,
            "exchange": 0,
            "exchange_limit_once": 4,
            "grant_type": 0,
            "icon": 0,
            "item_id": 1412,
            "item_name": "Onyx Ring (X)",
            "item_type": 2,
            "new_date": 1483228800000,
            "num": 1,
            "price": 10,
            "price2": 0,
            "price3": 0,
            "price4": 0,
            "price5": 0,
            "price_gil": 0,
            "published_date": 1647936000000,
            "shop_type": 1431,
            "sort_num": 31,
            "stock": 0,
            "tab_group": -1
        },
        {
            "close_date": 1924905600000,
            "consume_item_id": 2,
            "consume_item_id2": -1,
            "consume_item_id3": -1,
            "consume_item_id4": -1,
            "consume_item_id5": -1,
            "consume_item_type": 99,
            "consume_item_type2": -1,
            "consume_item_type3": -1,
            "consume_item_type4": -1,
            "consume_item_type5": -1,
            "description": "",
            "eqsi_id": 313303,
            "exchange": 0,
            "exchange_limit_once": 4,
            "grant_type": 0,
            "icon": 0,
            "item_id": 1439,
            "item_name": "Warrior's Armguard (X)",
            "item_type": 2,
            "new_date": 1483228800000,
            "num": 1,
            "price": 10,
            "price2": 0,
            "price3": 0,
            "price4": 0,
            "price5": 0,
            "price_gil": 0,
            "published_date": 1647936000000,
            "shop_type": 1431,
            "sort_num": 32,
            "stock": 0,
            "tab_group": -1
        },
        {
            "close_date": 1924905600000,
            "consume_item_id": 2,
            "consume_item_id2": -1,
            "consume_item_id3": -1,
            "consume_item_id4": -1,
            "consume_item_id5": -1,
            "consume_item_type": 99,
            "consume_item_type2": -1,
            "consume_item_type3": -1,
            "consume_item_type4": -1,
            "consume_item_type5": -1,
            "description": "",
            "eqsi_id": 313304,
            "exchange": 0,
            "exchange_limit_once": 4,
            "grant_type": 0,
            "icon": 0,
            "item_id": 1449,
            "item_name": "Seymour's Robes (X)",
            "item_type": 2,
            "new_date": 1483228800000,
            "num": 1,
            "price": 10,
            "price2": 0,
            "price3": 0,
            "price4": 0,
            "price5": 0,
            "price_gil": 0,
            "published_date": 1647936000000,
            "shop_type": 1431,
            "sort_num": 33,
            "stock": 0,
            "tab_group": -1
        },
        {
            "close_date": 1924905600000,
            "consume_item_id": 2,
            "consume_item_id2": -1,
            "consume_item_id3": -1,
            "consume_item_id4": -1,
            "consume_item_id5": -1,
            "consume_item_type": 99,
            "consume_item_type2": -1,
            "consume_item_type3": -1,
            "consume_item_type4": -1,
            "consume_item_type5": -1,
            "description": "",
            "eqsi_id": 313305,
            "exchange": 0,
            "exchange_limit_once": 4,
            "grant_type": 0,
            "icon": 0,
            "item_id": 1460,
            "item_name": "Jecht's Bandanna (X)",
            "item_type": 2,
            "new_date": 1483228800000,
            "num": 1,
            "price": 10,
            "price2": 0,
            "price3": 0,
            "price4": 0,
            "price5": 0,
            "price_gil": 0,
            "published_date": 1647936000000,
            "shop_type": 1431,
            "sort_num": 34,
            "stock": 0,
            "tab_group": -1
        },
        {
            "close_date": 1924905600000,
            "consume_item_id": 2,
            "consume_item_id2": -1,
            "consume_item_id3": -1,
            "consume_item_id4": -1,
            "consume_item_id5": -1,
            "consume_item_type": 99,
            "consume_item_type2": -1,
            "consume_item_type3": -1,
            "consume_item_type4": -1,
            "consume_item_type5": -1,
            "description": "",
            "eqsi_id": 313306,
            "exchange": 0,
            "exchange_limit_once": 4,
            "grant_type": 0,
            "icon": 0,
            "item_id": 1430,
            "item_name": "Wizard's Coat (XI)",
            "item_type": 2,
            "new_date": 1483228800000,
            "num": 1,
            "price": 10,
            "price2": 0,
            "price3": 0,
            "price4": 0,
            "price5": 0,
            "price_gil": 0,
            "published_date": 1647936000000,
            "shop_type": 1431,
            "sort_num": 35,
            "stock": 0,
            "tab_group": -1
        },
        {
            "close_date": 1924905600000,
            "consume_item_id": 2,
            "consume_item_id2": -1,
            "consume_item_id3": -1,
            "consume_item_id4": -1,
            "consume_item_id5": -1,
            "consume_item_type": 99,
            "consume_item_type2": -1,
            "consume_item_type3": -1,
            "consume_item_type4": -1,
            "consume_item_type5": -1,
            "description": "",
            "eqsi_id": 313307,
            "exchange": 0,
            "exchange_limit_once": 4,
            "grant_type": 0,
            "icon": 0,
            "item_id": 1441,
            "item_name": "Temple Cyclas (XI)",
            "item_type": 2,
            "new_date": 1483228800000,
            "num": 1,
            "price": 10,
            "price2": 0,
            "price3": 0,
            "price4": 0,
            "price5": 0,
            "price_gil": 0,
            "published_date": 1647936000000,
            "shop_type": 1431,
            "sort_num": 36,
            "stock": 0,
            "tab_group": -1
        },
        {
            "close_date": 1924905600000,
            "consume_item_id": 2,
            "consume_item_id2": -1,
            "consume_item_id3": -1,
            "consume_item_id4": -1,
            "consume_item_id5": -1,
            "consume_item_type": 99,
            "consume_item_type2": -1,
            "consume_item_type3": -1,
            "consume_item_type4": -1,
            "consume_item_type5": -1,
            "description": "",
            "eqsi_id": 313308,
            "exchange": 0,
            "exchange_limit_once": 4,
            "grant_type": 0,
            "icon": 0,
            "item_id": 1461,
            "item_name": "Dancer's Casaque (XI)",
            "item_type": 2,
            "new_date": 1483228800000,
            "num": 1,
            "price": 10,
            "price2": 0,
            "price3": 0,
            "price4": 0,
            "price5": 0,
            "price_gil": 0,
            "published_date": 1647936000000,
            "shop_type": 1431,
            "sort_num": 37,
            "stock": 0,
            "tab_group": -1
        },
        {
            "close_date": 1924905600000,
            "consume_item_id": 2,
            "consume_item_id2": -1,
            "consume_item_id3": -1,
            "consume_item_id4": -1,
            "consume_item_id5": -1,
            "consume_item_type": 99,
            "consume_item_type2": -1,
            "consume_item_type3": -1,
            "consume_item_type4": -1,
            "consume_item_type5": -1,
            "description": "",
            "eqsi_id": 313309,
            "exchange": 0,
            "exchange_limit_once": 4,
            "grant_type": 0,
            "icon": 0,
            "item_id": 1410,
            "item_name": "Round Shield (XII)",
            "item_type": 2,
            "new_date": 1483228800000,
            "num": 1,
            "price": 10,
            "price2": 0,
            "price3": 0,
            "price4": 0,
            "price5": 0,
            "price_gil": 0,
            "published_date": 1647936000000,
            "shop_type": 1431,
            "sort_num": 38,
            "stock": 0,
            "tab_group": -1
        },
        {
            "close_date": 1924905600000,
            "consume_item_id": 2,
            "consume_item_id2": -1,
            "consume_item_id3": -1,
            "consume_item_id4": -1,
            "consume_item_id5": -1,
            "consume_item_type": 99,
            "consume_item_type2": -1,
            "consume_item_type3": -1,
            "consume_item_type4": -1,
            "consume_item_type5": -1,
            "description": "",
            "eqsi_id": 313310,
            "exchange": 0,
            "exchange_limit_once": 4,
            "grant_type": 0,
            "icon": 0,
            "item_id": 1418,
            "item_name": "Traveler's Vestment (XII)",
            "item_type": 2,
            "new_date": 1483228800000,
            "num": 1,
            "price": 10,
            "price2": 0,
            "price3": 0,
            "price4": 0,
            "price5": 0,
            "price_gil": 0,
            "published_date": 1647936000000,
            "shop_type": 1431,
            "sort_num": 39,
            "stock": 0,
            "tab_group": -1
        },
        {
            "close_date": 1924905600000,
            "consume_item_id": 2,
            "consume_item_id2": -1,
            "consume_item_id3": -1,
            "consume_item_id4": -1,
            "consume_item_id5": -1,
            "consume_item_type": 99,
            "consume_item_type2": -1,
            "consume_item_type3": -1,
            "consume_item_type4": -1,
            "consume_item_type5": -1,
            "description": "",
            "eqsi_id": 313311,
            "exchange": 0,
            "exchange_limit_once": 4,
            "grant_type": 0,
            "icon": 0,
            "item_id": 1431,
            "item_name": "Rose Corsage (XII)",
            "item_type": 2,
            "new_date": 1483228800000,
            "num": 1,
            "price": 10,
            "price2": 0,
            "price3": 0,
            "price4": 0,
            "price5": 0,
            "price_gil": 0,
            "published_date": 1647936000000,
            "shop_type": 1431,
            "sort_num": 40,
            "stock": 0,
            "tab_group": -1
        },
        {
            "close_date": 1924905600000,
            "consume_item_id": 2,
            "consume_item_id2": -1,
            "consume_item_id3": -1,
            "consume_item_id4": -1,
            "consume_item_id5": -1,
            "consume_item_type": 99,
            "consume_item_type2": -1,
            "consume_item_type3": -1,
            "consume_item_type4": -1,
            "consume_item_type5": -1,
            "description": "",
            "eqsi_id": 313312,
            "exchange": 0,
            "exchange_limit_once": 4,
            "grant_type": 0,
            "icon": 0,
            "item_id": 1427,
            "item_name": "Aurora Scarf (XIII)",
            "item_type": 2,
            "new_date": 1483228800000,
            "num": 1,
            "price": 10,
            "price2": 0,
            "price3": 0,
            "price4": 0,
            "price5": 0,
            "price_gil": 0,
            "published_date": 1647936000000,
            "shop_type": 1431,
            "sort_num": 41,
            "stock": 0,
            "tab_group": -1
        },
        {
            "close_date": 1924905600000,
            "consume_item_id": 2,
            "consume_item_id2": -1,
            "consume_item_id3": -1,
            "consume_item_id4": -1,
            "consume_item_id5": -1,
            "consume_item_type": 99,
            "consume_item_type2": -1,
            "consume_item_type3": -1,
            "consume_item_type4": -1,
            "consume_item_type5": -1,
            "description": "",
            "eqsi_id": 313313,
            "exchange": 0,
            "exchange_limit_once": 4,
            "grant_type": 0,
            "icon": 0,
            "item_id": 1404,
            "item_name": "Ceramic Armband (XIII)",
            "item_type": 2,
            "new_date": 1483228800000,
            "num": 1,
            "price": 10,
            "price2": 0,
            "price3": 0,
            "price4": 0,
            "price5": 0,
            "price_gil": 0,
            "published_date": 1647936000000,
            "shop_type": 1431,
            "sort_num": 42,
            "stock": 0,
            "tab_group": -1
        },
        {
            "close_date": 1924905600000,
            "consume_item_id": 2,
            "consume_item_id2": -1,
            "consume_item_id3": -1,
            "consume_item_id4": -1,
            "consume_item_id5": -1,
            "consume_item_type": 99,
            "consume_item_type2": -1,
            "consume_item_type3": -1,
            "consume_item_type4": -1,
            "consume_item_type5": -1,
            "description": "",
            "eqsi_id": 313314,
            "exchange": 0,
            "exchange_limit_once": 4,
            "grant_type": 0,
            "icon": 0,
            "item_id": 1407,
            "item_name": "Power Gloves (XIII)",
            "item_type": 2,
            "new_date": 1483228800000,
            "num": 1,
            "price": 10,
            "price2": 0,
            "price3": 0,
            "price4": 0,
            "price5": 0,
            "price_gil": 0,
            "published_date": 1647936000000,
            "shop_type": 1431,
            "sort_num": 43,
            "stock": 0,
            "tab_group": -1
        },
        {
            "close_date": 1924905600000,
            "consume_item_id": 2,
            "consume_item_id2": -1,
            "consume_item_id3": -1,
            "consume_item_id4": -1,
            "consume_item_id5": -1,
            "consume_item_type": 99,
            "consume_item_type2": -1,
            "consume_item_type3": -1,
            "consume_item_type4": -1,
            "consume_item_type5": -1,
            "description": "",
            "eqsi_id": 313315,
            "exchange": 0,
            "exchange_limit_once": 4,
            "grant_type": 0,
            "icon": 0,
            "item_id": 1437,
            "item_name": "Rune Bracelet (XIII)",
            "item_type": 2,
            "new_date": 1483228800000,
            "num": 1,
            "price": 10,
            "price2": 0,
            "price3": 0,
            "price4": 0,
            "price5": 0,
            "price_gil": 0,
            "published_date": 1647936000000,
            "shop_type": 1431,
            "sort_num": 44,
            "stock": 0,
            "tab_group": -1
        },
        {
            "close_date": 1924905600000,
            "consume_item_id": 2,
            "consume_item_id2": -1,
            "consume_item_id3": -1,
            "consume_item_id4": -1,
            "consume_item_id5": -1,
            "consume_item_type": 99,
            "consume_item_type2": -1,
            "consume_item_type3": -1,
            "consume_item_type4": -1,
            "consume_item_type5": -1,
            "description": "",
            "eqsi_id": 313316,
            "exchange": 0,
            "exchange_limit_once": 4,
            "grant_type": 0,
            "icon": 0,
            "item_id": 1454,
            "item_name": "Cherub's Crown (XIII)",
            "item_type": 2,
            "new_date": 1483228800000,
            "num": 1,
            "price": 10,
            "price2": 0,
            "price3": 0,
            "price4": 0,
            "price5": 0,
            "price_gil": 0,
            "published_date": 1647936000000,
            "shop_type": 1431,
            "sort_num": 45,
            "stock": 0,
            "tab_group": -1
        },
        {
            "close_date": 1924905600000,
            "consume_item_id": 2,
            "consume_item_id2": -1,
            "consume_item_id3": -1,
            "consume_item_id4": -1,
            "consume_item_id5": -1,
            "consume_item_type": 99,
            "consume_item_type2": -1,
            "consume_item_type3": -1,
            "consume_item_type4": -1,
            "consume_item_type5": -1,
            "description": "",
            "eqsi_id": 313317,
            "exchange": 0,
            "exchange_limit_once": 4,
            "grant_type": 0,
            "icon": 0,
            "item_id": 1408,
            "item_name": "Imperial Operative Dalmatica (XIV)",
            "item_type": 2,
            "new_date": 1483228800000,
            "num": 1,
            "price": 10,
            "price2": 0,
            "price3": 0,
            "price4": 0,
            "price5": 0,
            "price_gil": 0,
            "published_date": 1647936000000,
            "shop_type": 1431,
            "sort_num": 46,
            "stock": 0,
            "tab_group": -1
        },
        {
            "close_date": 1924905600000,
            "consume_item_id": 2,
            "consume_item_id2": -1,
            "consume_item_id3": -1,
            "consume_item_id4": -1,
            "consume_item_id5": -1,
            "consume_item_type": 99,
            "consume_item_type2": -1,
            "consume_item_type3": -1,
            "consume_item_type4": -1,
            "consume_item_type5": -1,
            "description": "",
            "eqsi_id": 313318,
            "exchange": 0,
            "exchange_limit_once": 4,
            "grant_type": 0,
            "icon": 0,
            "item_id": 1411,
            "item_name": "Woolen Shirt (XIV)",
            "item_type": 2,
            "new_date": 1483228800000,
            "num": 1,
            "price": 10,
            "price2": 0,
            "price3": 0,
            "price4": 0,
            "price5": 0,
            "price_gil": 0,
            "published_date": 1647936000000,
            "shop_type": 1431,
            "sort_num": 47,
            "stock": 0,
            "tab_group": -1
        },
        {
            "close_date": 1924905600000,
            "consume_item_id": 2,
            "consume_item_id2": -1,
            "consume_item_id3": -1,
            "consume_item_id4": -1,
            "consume_item_id5": -1,
            "consume_item_type": 99,
            "consume_item_type2": -1,
            "consume_item_type3": -1,
            "consume_item_type4": -1,
            "consume_item_type5": -1,
            "description": "",
            "eqsi_id": 313319,
            "exchange": 0,
            "exchange_limit_once": 4,
            "grant_type": 0,
            "icon": 0,
            "item_id": 1452,
            "item_name": "Militia Robe (XIV)",
            "item_type": 2,
            "new_date": 1483228800000,
            "num": 1,
            "price": 10,
            "price2": 0,
            "price3": 0,
            "price4": 0,
            "price5": 0,
            "price_gil": 0,
            "published_date": 1647936000000,
            "shop_type": 1431,
            "sort_num": 48,
            "stock": 0,
            "tab_group": -1
        },
        {
            "close_date": 1924905600000,
            "consume_item_id": 2,
            "consume_item_id2": -1,
            "consume_item_id3": -1,
            "consume_item_id4": -1,
            "consume_item_id5": -1,
            "consume_item_type": 99,
            "consume_item_type2": -1,
            "consume_item_type3": -1,
            "consume_item_type4": -1,
            "consume_item_type5": -1,
            "description": "",
            "eqsi_id": 313320,
            "exchange": 0,
            "exchange_limit_once": 4,
            "grant_type": 0,
            "icon": 0,
            "item_id": 1443,
            "item_name": "Adamant Vest (FFT)",
            "item_type": 2,
            "new_date": 1483228800000,
            "num": 1,
            "price": 10,
            "price2": 0,
            "price3": 0,
            "price4": 0,
            "price5": 0,
            "price_gil": 0,
            "published_date": 1647936000000,
            "shop_type": 1431,
            "sort_num": 49,
            "stock": 0,
            "tab_group": -1
        },
        {
            "close_date": 1924905600000,
            "consume_item_id": 2,
            "consume_item_id2": -1,
            "consume_item_id3": -1,
            "consume_item_id4": -1,
            "consume_item_id5": -1,
            "consume_item_type": 99,
            "consume_item_type2": -1,
            "consume_item_type3": -1,
            "consume_item_type4": -1,
            "consume_item_type5": -1,
            "description": "",
            "eqsi_id": 313321,
            "exchange": 0,
            "exchange_limit_once": 4,
            "grant_type": 0,
            "icon": 0,
            "item_id": 1448,
            "item_name": "Suzaku's Hood (0)",
            "item_type": 2,
            "new_date": 1483228800000,
            "num": 1,
            "price": 10,
            "price2": 0,
            "price3": 0,
            "price4": 0,
            "price5": 0,
            "price_gil": 0,
            "published_date": 1647936000000,
            "shop_type": 1431,
            "sort_num": 50,
            "stock": 0,
            "tab_group": -1
        },
        {
            "close_date": 1924905600000,
            "consume_item_id": 2,
            "consume_item_id2": -1,
            "consume_item_id3": -1,
            "consume_item_id4": -1,
            "consume_item_id5": -1,
            "consume_item_type": 99,
            "consume_item_type2": -1,
            "consume_item_type3": -1,
            "consume_item_type4": -1,
            "consume_item_type5": -1,
            "description": "",
            "eqsi_id": 313322,
            "exchange": 0,
            "exchange_limit_once": 4,
            "grant_type": 0,
            "icon": 0,
            "item_id": 1403,
            "item_name": "Circlet (0)",
            "item_type": 2,
            "new_date": 1483228800000,
            "num": 1,
            "price": 10,
            "price2": 0,
            "price3": 0,
            "price4": 0,
            "price5": 0,
            "price_gil": 0,
            "published_date": 1647936000000,
            "shop_type": 1431,
            "sort_num": 51,
            "stock": 0,
            "tab_group": -1
        },
        {
            "close_date": 1924905600000,
            "consume_item_id": 2,
            "consume_item_id2": -1,
            "consume_item_id3": -1,
            "consume_item_id4": -1,
            "consume_item_id5": -1,
            "consume_item_type": 99,
            "consume_item_type2": -1,
            "consume_item_type3": -1,
            "consume_item_type4": -1,
            "consume_item_type5": -1,
            "description": "",
            "eqsi_id": 313323,
            "exchange": 0,
            "exchange_limit_once": 4,
            "grant_type": 0,
            "icon": 0,
            "item_id": 1415,
            "item_name": "Ballistic Armor (0)",
            "item_type": 2,
            "new_date": 1483228800000,
            "num": 1,
            "price": 10,
            "price2": 0,
            "price3": 0,
            "price4": 0,
            "price5": 0,
            "price_gil": 0,
            "published_date": 1647936000000,
            "shop_type": 1431,
            "sort_num": 52,
            "stock": 0,
            "tab_group": -1
        },
        {
            "close_date": 1924905600000,
            "consume_item_id": 2,
            "consume_item_id2": -1,
            "consume_item_id3": -1,
            "consume_item_id4": -1,
            "consume_item_id5": -1,
            "consume_item_type": 99,
            "consume_item_type2": -1,
            "consume_item_type3": -1,
            "consume_item_type4": -1,
            "consume_item_type5": -1,
            "description": "",
            "eqsi_id": 313324,
            "exchange": 0,
            "exchange_limit_once": 4,
            "grant_type": 0,
            "icon": 0,
            "item_id": 1462,
            "item_name": "Bronze Helm (FFCC)",
            "item_type": 2,
            "new_date": 1483228800000,
            "num": 1,
            "price": 10,
            "price2": 0,
            "price3": 0,
            "price4": 0,
            "price5": 0,
            "price_gil": 0,
            "published_date": 1647936000000,
            "shop_type": 1431,
            "sort_num": 53,
            "stock": 0,
            "tab_group": -1
        },
        {
            "close_date": 1924905600000,
            "consume_item_id": 2,
            "consume_item_id2": -1,
            "consume_item_id3": -1,
            "consume_item_id4": -1,
            "consume_item_id5": -1,
            "consume_item_type": 99,
            "consume_item_type2": -1,
            "consume_item_type3": -1,
            "consume_item_type4": -1,
            "consume_item_type5": -1,
            "description": "",
            "eqsi_id": 313325,
            "exchange": 0,
            "exchange_limit_once": 4,
            "grant_type": 0,
            "icon": 0,
            "item_id": 1445,
            "item_name": "Layle's Goggles (FFCC)",
            "item_type": 2,
            "new_date": 1483228800000,
            "num": 1,
            "price": 10,
            "price2": 0,
            "price3": 0,
            "price4": 0,
            "price5": 0,
            "price_gil": 0,
            "published_date": 1647936000000,
            "shop_type": 1431,
            "sort_num": 54,
            "stock": 0,
            "tab_group": -1
        }
    ],
    "shop_group": 0,
    "shop_name": "Gem Exchange (4 Armor)",
    "shop_type": 1431,
    "status_code": 0,
    "verup_code": 0
}