{
    "fields": [
        {
            "field_id": 911,
            "field_part": 0,
            "quests": [
                {
                    "difficulty": 0,
                    "difficulty_mode": 0,
                    "is_clear": 0,
                    "is_strong_enemy": 0,
                    "items": [],
                    "name": "0",
                    "quest_id": 33524,
                    "quest_type": 6
                },
                {
                    "difficulty": 0,
                    "difficulty_mode": 0,
                    "is_clear": 0,
                    "is_strong_enemy": 0,
                    "items": [],
                    "name": "0",
                    "quest_id": 33525,
                    "quest_type": 6
                },
                {
                    "difficulty": 0,
                    "difficulty_mode": 0,
                    "is_clear": 0,
                    "is_strong_enemy": 0,
                    "items": [],
                    "name": "0",
                    "quest_id": 33526,
                    "quest_type": 6
                },
                {
                    "difficulty": 0,
                    "difficulty_mode": 0,
                    "is_clear": 0,
                    "is_strong_enemy": 0,
                    "items": [],
                    "name": "0",
                    "quest_id": 33527,
                    "quest_type": 6
                },
                {
                    "difficulty": 0,
                    "difficulty_mode": 0,
                    "is_clear": 0,
                    "is_strong_enemy": 0,
                    "items": [],
                    "name": "0",
                    "quest_id": 33528,
                    "quest_type": 6
                },
                {
                    "difficulty": 0,
                    "difficulty_mode": 0,
                    "is_clear": 0,
                    "is_strong_enemy": 0,
                    "items": [],
                    "name": "0",
                    "quest_id": 33529,
                    "quest_type": 6
                },
                {
                    "difficulty": 0,
                    "difficulty_mode": 0,
                    "is_clear": 0,
                    "is_strong_enemy": 0,
                    "items": [],
                    "name": "0",
                    "quest_id": 33530,
                    "quest_type": 6
                },
                {
                    "difficulty": 0,
                    "difficulty_mode": 0,
                    "is_clear": 0,
                    "is_strong_enemy": 0,
                    "items": [],
                    "name": "0",
                    "quest_id": 33531,
                    "quest_type": 6
                },
                {
                    "difficulty": 0,
                    "difficulty_mode": 0,
                    "is_clear": 0,
                    "is_strong_enemy": 0,
                    "items": [],
                    "name": "0",
                    "quest_id": 33532,
                    "quest_type": 6
                },
                {
                    "difficulty": 0,
                    "difficulty_mode": 0,
                    "is_clear": 0,
                    "is_strong_enemy": 0,
                    "items": [],
                    "name": "0",
                    "quest_id": 33533,
                    "quest_type": 6
                },
                {
                    "difficulty": 0,
                    "difficulty_mode": 0,
                    "is_clear": 0,
                    "is_strong_enemy": 0,
                    "items": [],
                    "name": "0",
                    "quest_id": 33534,
                    "quest_type": 6
                },
                {
                    "difficulty": 0,
                    "difficulty_mode": 0,
                    "is_clear": 0,
                    "is_strong_enemy": 0,
                    "items": [],
                    "name": "0",
                    "quest_id": 33535,
                    "quest_type": 6
                },
                {
                    "difficulty": 0,
                    "difficulty_mode": 0,
                    "is_clear": 0,
                    "is_strong_enemy": 0,
                    "items": [],
                    "name": "0",
                    "quest_id": 33536,
                    "quest_type": 6
                },
                {
                    "difficulty": 0,
                    "difficulty_mode": 0,
                    "is_clear": 0,
                    "is_strong_enemy": 0,
                    "items": [],
                    "name": "0",
                    "quest_id": 33537,
                    "quest_type": 6
                },
                {
                    "difficulty": 0,
                    "difficulty_mode": 0,
                    "is_clear": 0,
                    "is_strong_enemy": 0,
                    "items": [],
                    "name": "0",
                    "quest_id": 33538,
                    "quest_type": 6
                },
                {
                    "difficulty": 0,
                    "difficulty_mode": 0,
                    "is_clear": 0,
                    "is_strong_enemy": 0,
                    "items": [],
                    "name": "0",
                    "quest_id": 33539,
                    "quest_type": 6
                },
                {
                    "difficulty": 0,
                    "difficulty_mode": 0,
                    "is_clear": 0,
                    "is_strong_enemy": 0,
                    "items": [],
                    "name": "0",
                    "quest_id": 33540,
                    "quest_type": 6
                },
                {
                    "difficulty": 0,
                    "difficulty_mode": 0,
                    "is_clear": 0,
                    "is_strong_enemy": 0,
                    "items": [],
                    "name": "0",
                    "quest_id": 33541,
                    "quest_type": 6
                },
                {
                    "difficulty": 0,
                    "difficulty_mode": 0,
                    "is_clear": 0,
                    "is_strong_enemy": 0,
                    "items": [],
                    "name": "0",
                    "quest_id": 33542,
                    "quest_type": 6
                },
                {
                    "difficulty": 0,
                    "difficulty_mode": 0,
                    "is_clear": 0,
                    "is_strong_enemy": 0,
                    "items": [],
                    "name": "0",
                    "quest_id": 33543,
                    "quest_type": 6
                },
                {
                    "difficulty": 0,
                    "difficulty_mode": 0,
                    "is_clear": 0,
                    "is_strong_enemy": 0,
                    "items": [],
                    "name": "0",
                    "quest_id": 33544,
                    "quest_type": 6
                },
                {
                    "difficulty": 0,
                    "difficulty_mode": 0,
                    "is_clear": 0,
                    "is_strong_enemy": 0,
                    "items": [],
                    "name": "0",
                    "quest_id": 33545,
                    "quest_type": 6
                },
                {
                    "difficulty": 0,
                    "difficulty_mode": 0,
                    "is_clear": 0,
                    "is_strong_enemy": 0,
                    "items": [],
                    "name": "0",
                    "quest_id": 33546,
                    "quest_type": 6
                },
                {
                    "difficulty": 0,
                    "difficulty_mode": 0,
                    "is_clear": 0,
                    "is_strong_enemy": 0,
                    "items": [],
                    "name": "0",
                    "quest_id": 33547,
                    "quest_type": 6
                },
                {
                    "difficulty": 0,
                    "difficulty_mode": 0,
                    "is_clear": 0,
                    "is_strong_enemy": 0,
                    "items": [],
                    "name": "0",
                    "quest_id": 33548,
                    "quest_type": 6
                },
                {
                    "difficulty": 0,
                    "difficulty_mode": 0,
                    "is_clear": 0,
                    "is_strong_enemy": 0,
                    "items": [],
                    "name": "0",
                    "quest_id": 33549,
                    "quest_type": 6
                },
                {
                    "difficulty": 0,
                    "difficulty_mode": 0,
                    "is_clear": 0,
                    "is_strong_enemy": 0,
                    "items": [],
                    "name": "0",
                    "quest_id": 33550,
                    "quest_type": 6
                },
                {
                    "difficulty": 0,
                    "difficulty_mode": 0,
                    "is_clear": 0,
                    "is_strong_enemy": 0,
                    "items": [],
                    "name": "0",
                    "quest_id": 33551,
                    "quest_type": 6
                },
                {
                    "difficulty": 0,
                    "difficulty_mode": 0,
                    "is_clear": 0,
                    "is_strong_enemy": 0,
                    "items": [],
                    "name": "0",
                    "quest_id": 33552,
                    "quest_type": 6
                },
                {
                    "difficulty": 0,
                    "difficulty_mode": 0,
                    "is_clear": 0,
                    "is_strong_enemy": 0,
                    "items": [],
                    "name": "0",
                    "quest_id": 33553,
                    "quest_type": 6
                },
                {
                    "difficulty": 0,
                    "difficulty_mode": 0,
                    "is_clear": 0,
                    "is_strong_enemy": 0,
                    "items": [],
                    "name": "0",
                    "quest_id": 33554,
                    "quest_type": 6
                },
                {
                    "difficulty": 0,
                    "difficulty_mode": 0,
                    "is_clear": 0,
                    "is_strong_enemy": 0,
                    "items": [],
                    "name": "0",
                    "quest_id": 33555,
                    "quest_type": 6
                },
                {
                    "difficulty": 0,
                    "difficulty_mode": 0,
                    "is_clear": 0,
                    "is_strong_enemy": 0,
                    "items": [],
                    "name": "0",
                    "quest_id": 33556,
                    "quest_type": 6
                },
                {
                    "difficulty": 0,
                    "difficulty_mode": 0,
                    "is_clear": 0,
                    "is_strong_enemy": 0,
                    "items": [],
                    "name": "0",
                    "quest_id": 33557,
                    "quest_type": 6
                },
                {
                    "difficulty": 0,
                    "difficulty_mode": 0,
                    "is_clear": 0,
                    "is_strong_enemy": 0,
                    "items": [],
                    "name": "0",
                    "quest_id": 33558,
                    "quest_type": 6
                },
                {
                    "difficulty": 0,
                    "difficulty_mode": 0,
                    "is_clear": 0,
                    "is_strong_enemy": 0,
                    "items": [],
                    "name": "0",
                    "quest_id": 33559,
                    "quest_type": 6
                },
                {
                    "difficulty": 0,
                    "difficulty_mode": 0,
                    "is_clear": 0,
                    "is_strong_enemy": 0,
                    "items": [],
                    "name": "0",
                    "quest_id": 33560,
                    "quest_type": 6
                },
                {
                    "difficulty": 0,
                    "difficulty_mode": 0,
                    "is_clear": 0,
                    "is_strong_enemy": 0,
                    "items": [],
                    "name": "0",
                    "quest_id": 33561,
                    "quest_type": 4
                },
                {
                    "difficulty": 0,
                    "difficulty_mode": 0,
                    "is_clear": 0,
                    "is_strong_enemy": 0,
                    "items": [],
                    "name": "0",
                    "quest_id": 33562,
                    "quest_type": 4
                },
                {
                    "difficulty": 0,
                    "difficulty_mode": 0,
                    "is_clear": 0,
                    "is_strong_enemy": 0,
                    "items": [],
                    "name": "0",
                    "quest_id": 33563,
                    "quest_type": 4
                },
                {
                    "difficulty": 0,
                    "difficulty_mode": 0,
                    "is_clear": 0,
                    "is_strong_enemy": 0,
                    "items": [],
                    "name": "0",
                    "quest_id": 33564,
                    "quest_type": 4
                },
                {
                    "difficulty": 0,
                    "difficulty_mode": 0,
                    "is_clear": 0,
                    "is_strong_enemy": 0,
                    "items": [],
                    "name": "0",
                    "quest_id": 33565,
                    "quest_type": 4
                },
                {
                    "difficulty": 0,
                    "difficulty_mode": 0,
                    "is_clear": 0,
                    "is_strong_enemy": 0,
                    "items": [],
                    "name": "0",
                    "quest_id": 33566,
                    "quest_type": 4
                },
                {
                    "difficulty": 0,
                    "difficulty_mode": 0,
                    "is_clear": 0,
                    "is_strong_enemy": 0,
                    "items": [],
                    "name": "0",
                    "quest_id": 33567,
                    "quest_type": 4
                },
                {
                    "difficulty": 0,
                    "difficulty_mode": 0,
                    "is_clear": 0,
                    "is_strong_enemy": 0,
                    "items": [],
                    "name": "0",
                    "quest_id": 33568,
                    "quest_type": 4
                },
                {
                    "difficulty": 0,
                    "difficulty_mode": 0,
                    "is_clear": 0,
                    "is_strong_enemy": 0,
                    "items": [],
                    "name": "0",
                    "quest_id": 33569,
                    "quest_type": 4
                },
                {
                    "difficulty": 0,
                    "difficulty_mode": 0,
                    "is_clear": 0,
                    "is_strong_enemy": 0,
                    "items": [],
                    "name": "0",
                    "quest_id": 33570,
                    "quest_type": 4
                },
                {
                    "difficulty": 0,
                    "difficulty_mode": 0,
                    "is_clear": 0,
                    "is_strong_enemy": 0,
                    "items": [],
                    "name": "0",
                    "quest_id": 33571,
                    "quest_type": 4
                },
                {
                    "difficulty": 0,
                    "difficulty_mode": 0,
                    "is_clear": 0,
                    "is_strong_enemy": 0,
                    "items": [],
                    "name": "0",
                    "quest_id": 33572,
                    "quest_type": 4
                },
                {
                    "difficulty": 0,
                    "difficulty_mode": 0,
                    "is_clear": 0,
                    "is_strong_enemy": 0,
                    "items": [],
                    "name": "0",
                    "quest_id": 33573,
                    "quest_type": 4
                },
                {
                    "difficulty": 0,
                    "difficulty_mode": 0,
                    "is_clear": 0,
                    "is_strong_enemy": 0,
                    "items": [],
                    "name": "0",
                    "quest_id": 33574,
                    "quest_type": 4
                },
                {
                    "difficulty": 0,
                    "difficulty_mode": 0,
                    "is_clear": 0,
                    "is_strong_enemy": 0,
                    "items": [],
                    "name": "0",
                    "quest_id": 33575,
                    "quest_type": 4
                },
                {
                    "difficulty": 0,
                    "difficulty_mode": 0,
                    "is_clear": 0,
                    "is_strong_enemy": 0,
                    "items": [],
                    "name": "Stairs 1",
                    "quest_id": 33594,
                    "quest_type": 11
                },
                {
                    "difficulty": 0,
                    "difficulty_mode": 0,
                    "is_clear": 0,
                    "is_strong_enemy": 0,
                    "items": [],
                    "name": "Stairs 2",
                    "quest_id": 33595,
                    "quest_type": 11
                },
                {
                    "difficulty": 0,
                    "difficulty_mode": 0,
                    "is_clear": 0,
                    "is_strong_enemy": 0,
                    "items": [],
                    "name": "Stairs 3",
                    "quest_id": 33596,
                    "quest_type": 11
                },
                {
                    "difficulty": 0,
                    "difficulty_mode": 0,
                    "is_clear": 0,
                    "is_strong_enemy": 0,
                    "items": [],
                    "name": "Stairs 4",
                    "quest_id": 33597,
                    "quest_type": 11
                },
                {
                    "difficulty": 0,
                    "difficulty_mode": 0,
                    "is_clear": 0,
                    "is_strong_enemy": 0,
                    "items": [],
                    "name": "Stairs 5",
                    "quest_id": 33598,
                    "quest_type": 11
                },
                {
                    "difficulty": 0,
                    "difficulty_mode": 0,
                    "is_clear": 0,
                    "is_strong_enemy": 0,
                    "items": [],
                    "name": "0",
                    "quest_id": 33600,
                    "quest_type": 3
                },
                {
                    "difficulty": 115,
                    "difficulty_mode": 1,
                    "is_clear": 0,
                    "is_strong_enemy": 1,
                    "items": [],
                    "name": "Normalis 4th Stratum Pt. 1",
                    "quest_id": 33605,
                    "quest_missions": [
                        {
                            "complete": 0,
                            "level": 0,
                            "missions": [
                                {
                                    "history": {
                                        "clear": 0,
                                        "progress": -1
                                    },
                                    "num": 4,
                                    "quest_mission": {
                                        "arg1": 430000,
                                        "arg2": -1,
                                        "clear": 0,
                                        "mission_type": 30,
                                        "mode": 2,
                                        "num": 4,
                                        "progress": -1,
                                        "rewards": [
                                            {
                                                "item_id": 2,
                                                "item_num": 50,
                                                "item_type": 99,
                                                "quest_reward_type": 3
                                            }
                                        ]
                                    },
                                    "require": 430000
                                }
                            ],
                            "perfect_cleared": 0,
                            "step": 1,
                            "this_perfect_clear": 0,
                            "this_perfect_clear2": 0
                        }
                    ],
                    "quest_type": 1
                },
                {
                    "difficulty": 0,
                    "difficulty_mode": 2,
                    "is_clear": 0,
                    "is_strong_enemy": 0,
                    "items": [],
                    "name": "Normalis 4th Stratum Pt. 1",
                    "quest_id": 33605,
                    "quest_type": 1
                },
                {
                    "difficulty": 90,
                    "difficulty_mode": 1,
                    "is_clear": 0,
                    "is_strong_enemy": 0,
                    "items": [],
                    "name": "Normalis 4th Stratum Pt. 2",
                    "quest_id": 33606,
                    "quest_missions": [
                        {
                            "complete": 0,
                            "level": 0,
                            "missions": [
                                {
                                    "history": {
                                        "clear": 0,
                                        "progress": -1
                                    },
                                    "num": 4,
                                    "quest_mission": {
                                        "arg1": 180000,
                                        "arg2": -1,
                                        "clear": 0,
                                        "mission_type": 30,
                                        "mode": 2,
                                        "num": 4,
                                        "progress": -1,
                                        "rewards": [
                                            {
                                                "item_id": 2,
                                                "item_num": 50,
                                                "item_type": 99,
                                                "quest_reward_type": 3
                                            }
                                        ]
                                    },
                                    "require": 180000
                                }
                            ],
                            "perfect_cleared": 0,
                            "step": 1,
                            "this_perfect_clear": 0,
                            "this_perfect_clear2": 0
                        }
                    ],
                    "quest_type": 1
                },
                {
                    "difficulty": 0,
                    "difficulty_mode": 2,
                    "is_clear": 0,
                    "is_strong_enemy": 0,
                    "items": [],
                    "name": "Normalis 4th Stratum Pt. 2",
                    "quest_id": 33606,
                    "quest_type": 1
                },
                {
                    "difficulty": 90,
                    "difficulty_mode": 1,
                    "is_clear": 0,
                    "is_strong_enemy": 0,
                    "items": [],
                    "name": "Normalis 4th Stratum Pt. 3",
                    "quest_id": 33607,
                    "quest_missions": [
                        {
                            "complete": 0,
                            "level": 0,
                            "missions": [
                                {
                                    "history": {
                                        "clear": 0,
                                        "progress": -1
                                    },
                                    "num": 4,
                                    "quest_mission": {
                                        "arg1": 180000,
                                        "arg2": -1,
                                        "clear": 0,
                                        "mission_type": 30,
                                        "mode": 2,
                                        "num": 4,
                                        "progress": -1,
                                        "rewards": [
                                            {
                                                "item_id": 2,
                                                "item_num": 50,
                                                "item_type": 99,
                                                "quest_reward_type": 3
                                            }
                                        ]
                                    },
                                    "require": 180000
                                }
                            ],
                            "perfect_cleared": 0,
                            "step": 1,
                            "this_perfect_clear": 0,
                            "this_perfect_clear2": 0
                        }
                    ],
                    "quest_type": 1
                },
                {
                    "difficulty": 0,
                    "difficulty_mode": 2,
                    "is_clear": 0,
                    "is_strong_enemy": 0,
                    "items": [],
                    "name": "Normalis 4th Stratum Pt. 3",
                    "quest_id": 33607,
                    "quest_type": 1
                },
                {
                    "difficulty": 115,
                    "difficulty_mode": 1,
                    "is_clear": 0,
                    "is_strong_enemy": 1,
                    "items": [],
                    "name": "Normalis 4th Stratum Pt. 4",
                    "quest_id": 33608,
                    "quest_missions": [
                        {
                            "complete": 0,
                            "level": 0,
                            "missions": [
                                {
                                    "history": {
                                        "clear": 0,
                                        "progress": -1
                                    },
                                    "num": 4,
                                    "quest_mission": {
                                        "arg1": 380000,
                                        "arg2": -1,
                                        "clear": 0,
                                        "mission_type": 30,
                                        "mode": 2,
                                        "num": 4,
                                        "progress": -1,
                                        "rewards": [
                                            {
                                                "item_id": 2,
                                                "item_num": 50,
                                                "item_type": 99,
                                                "quest_reward_type": 3
                                            }
                                        ]
                                    },
                                    "require": 380000
                                }
                            ],
                            "perfect_cleared": 0,
                            "step": 1,
                            "this_perfect_clear": 0,
                            "this_perfect_clear2": 0
                        }
                    ],
                    "quest_type": 1
                },
                {
                    "difficulty": 0,
                    "difficulty_mode": 2,
                    "is_clear": 0,
                    "is_strong_enemy": 0,
                    "items": [],
                    "name": "Normalis 4th Stratum Pt. 4",
                    "quest_id": 33608,
                    "quest_type": 1
                },
                {
                    "difficulty": 115,
                    "difficulty_mode": 1,
                    "is_clear": 0,
                    "is_strong_enemy": 1,
                    "items": [],
                    "name": "Normalis 4th Stratum Pt. 5",
                    "quest_id": 33609,
                    "quest_missions": [
                        {
                            "complete": 0,
                            "level": 0,
                            "missions": [
                                {
                                    "history": {
                                        "clear": 0,
                                        "progress": -1
                                    },
                                    "num": 4,
                                    "quest_mission": {
                                        "arg1": 340000,
                                        "arg2": -1,
                                        "clear": 0,
                                        "mission_type": 30,
                                        "mode": 2,
                                        "num": 4,
                                        "progress": -1,
                                        "rewards": [
                                            {
                                                "item_id": 2,
                                                "item_num": 50,
                                                "item_type": 99,
                                                "quest_reward_type": 3
                                            }
                                        ]
                                    },
                                    "require": 340000
                                }
                            ],
                            "perfect_cleared": 0,
                            "step": 1,
                            "this_perfect_clear": 0,
                            "this_perfect_clear2": 0
                        }
                    ],
                    "quest_type": 1
                },
                {
                    "difficulty": 0,
                    "difficulty_mode": 2,
                    "is_clear": 0,
                    "is_strong_enemy": 0,
                    "items": [],
                    "name": "Normalis 4th Stratum Pt. 5",
                    "quest_id": 33609,
                    "quest_type": 1
                },
                {
                    "difficulty": 115,
                    "difficulty_mode": 1,
                    "is_clear": 0,
                    "is_strong_enemy": 1,
                    "items": [],
                    "name": "Normalis 4th Stratum Pt. 6",
                    "quest_id": 33610,
                    "quest_missions": [
                        {
                            "complete": 0,
                            "level": 0,
                            "missions": [
                                {
                                    "history": {
                                        "clear": 0,
                                        "progress": -1
                                    },
                                    "num": 4,
                                    "quest_mission": {
                                        "arg1": 310000,
                                        "arg2": -1,
                                        "clear": 0,
                                        "mission_type": 30,
                                        "mode": 2,
                                        "num": 4,
                                        "progress": -1,
                                        "rewards": [
                                            {
                                                "item_id": 2,
                                                "item_num": 50,
                                                "item_type": 99,
                                                "quest_reward_type": 3
                                            }
                                        ]
                                    },
                                    "require": 310000
                                }
                            ],
                            "perfect_cleared": 0,
                            "step": 1,
                            "this_perfect_clear": 0,
                            "this_perfect_clear2": 0
                        }
                    ],
                    "quest_type": 1
                },
                {
                    "difficulty": 0,
                    "difficulty_mode": 2,
                    "is_clear": 0,
                    "is_strong_enemy": 0,
                    "items": [],
                    "name": "Normalis 4th Stratum Pt. 6",
                    "quest_id": 33610,
                    "quest_type": 1
                },
                {
                    "difficulty": 115,
                    "difficulty_mode": 1,
                    "is_clear": 0,
                    "is_strong_enemy": 1,
                    "items": [],
                    "name": "Normalis 4th Stratum Pt. 7",
                    "quest_id": 33611,
                    "quest_missions": [
                        {
                            "complete": 0,
                            "level": 0,
                            "missions": [
                                {
                                    "history": {
                                        "clear": 0,
                                        "progress": -1
                                    },
                                    "num": 4,
                                    "quest_mission": {
                                        "arg1": 280000,
                                        "arg2": -1,
                                        "clear": 0,
                                        "mission_type": 30,
                                        "mode": 2,
                                        "num": 4,
                                        "progress": -1,
                                        "rewards": [
                                            {
                                                "item_id": 2,
                                                "item_num": 50,
                                                "item_type": 99,
                                                "quest_reward_type": 3
                                            }
                                        ]
                                    },
                                    "require": 280000
                                }
                            ],
                            "perfect_cleared": 0,
                            "step": 1,
                            "this_perfect_clear": 0,
                            "this_perfect_clear2": 0
                        }
                    ],
                    "quest_type": 1
                },
                {
                    "difficulty": 0,
                    "difficulty_mode": 2,
                    "is_clear": 0,
                    "is_strong_enemy": 0,
                    "items": [],
                    "name": "Normalis 4th Stratum Pt. 7",
                    "quest_id": 33611,
                    "quest_type": 1
                },
                {
                    "difficulty": 150,
                    "difficulty_mode": 1,
                    "is_clear": 0,
                    "is_strong_enemy": 2,
                    "items": [],
                    "name": "Normalis 4th Stratum Pt. 8 COSMOS",
                    "quest_id": 33612,
                    "quest_missions": [
                        {
                            "complete": 0,
                            "level": 0,
                            "missions": [
                                {
                                    "history": {
                                        "clear": 0,
                                        "progress": -1
                                    },
                                    "num": 4,
                                    "quest_mission": {
                                        "arg1": 470000,
                                        "arg2": -1,
                                        "clear": 0,
                                        "mission_type": 30,
                                        "mode": 2,
                                        "num": 4,
                                        "progress": -1,
                                        "rewards": [
                                            {
                                                "item_id": 2,
                                                "item_num": 50,
                                                "item_type": 99,
                                                "quest_reward_type": 3
                                            }
                                        ]
                                    },
                                    "require": 470000
                                }
                            ],
                            "perfect_cleared": 0,
                            "step": 1,
                            "this_perfect_clear": 0,
                            "this_perfect_clear2": 0
                        }
                    ],
                    "quest_type": 1
                },
                {
                    "difficulty": 0,
                    "difficulty_mode": 2,
                    "is_clear": 0,
                    "is_strong_enemy": 0,
                    "items": [],
                    "name": "Normalis 4th Stratum Pt. 8 COSMOS",
                    "quest_id": 33612,
                    "quest_type": 1
                }
            ],
            "shop_items": []
        }
    ],
    "missions": [
        {
            "description": "Clear \\n\"Normalis 4th Stratum Pt. 8 COSMOS\"",
            "field_part": 0,
            "mission_category": 8,
            "mission_id": 9900084,
            "moogle_pass_receive_status": 0,
            "receive_status": 0,
            "rewards": [
                {
                    "item_id": 3,
                    "item_num": 3,
                    "item_type": 8
                }
            ]
        },
        {
            "description": "Clear \\n\"Normalis 4th Stratum Pt. 8 COSMOS\"",
            "field_part": 0,
            "mission_category": 8,
            "mission_id": 9900085,
            "moogle_pass_receive_status": 0,
            "receive_status": 0,
            "rewards": [
                {
                    "item_id": 3,
                    "item_num": 5,
                    "item_type": 18
                }
            ]
        },
        {
            "description": "Clear \\n\"Normalis 4th Stratum Pt. 8 COSMOS\"",
            "field_part": 0,
            "mission_category": 8,
            "mission_id": 9900086,
            "moogle_pass_receive_status": 0,
            "receive_status": 0,
            "rewards": [
                {
                    "item_id": 5,
                    "item_num": 5,
                    "item_type": 18
                }
            ]
        },
        {
            "description": "Complete \\n\"Normalis 4th Stratum Pt. 8 COSMOS\"",
            "field_part": 0,
            "mission_category": 8,
            "mission_id": 9900087,
            "moogle_pass_receive_status": 0,
            "receive_status": 0,
            "rewards": [
                {
                    "item_id": 3,
                    "item_num": 3,
                    "item_type": 8
                }
            ]
        },
        {
            "description": "Complete \\n\"Normalis 4th Stratum Pt. 8 COSMOS\"",
            "field_part": 0,
            "mission_category": 8,
            "mission_id": 9900088,
            "moogle_pass_receive_status": 0,
            "receive_status": 0,
            "rewards": [
                {
                    "item_id": 3,
                    "item_num": 5,
                    "item_type": 18
                }
            ]
        },
        {
            "description": "Complete \\n\"Normalis 4th Stratum Pt. 8 COSMOS\"",
            "field_part": 0,
            "mission_category": 8,
            "mission_id": 9900089,
            "moogle_pass_receive_status": 0,
            "receive_status": 0,
            "rewards": [
                {
                    "item_id": 5,
                    "item_num": 5,
                    "item_type": 18
                }
            ]
        }
    ],
    "summonboard": {}
}