{
    "before_talk": -1,
    "behavior_code": 0,
    "count_event": false,
    "difficulty_level": 0,
    "event_id": 0,
    "mission_clear": false,
    "nonce": "mhRhsm3qs7BmshqL",
    "postproc_opt": {
        "b_i": 0,
        "b_c": -1,
        "s_c": -1,
        "s_i": -1
    },
    "quest_sid": "haCq6h9EYq0E0YCY",
    "quest_start_date": 1702293033453,
    "status_code": 0,
    "support_user_id": 0,
    "unlocked_event": false,
    "use_battle_ticket": 0,
    "use_skip_ticket_id": 0,
    "verup_code": 0
}